generative_ai_toolkit/__init__.py
generative_ai_toolkit/exceptions.py
generative_ai_toolkit/agent/__init__.py
generative_ai_toolkit/agent/agent.py
generative_ai_toolkit/agent/bedrock_converse_agent.py
generative_ai_toolkit/agent/bedrock_converse_stream.py
generative_ai_toolkit/agent/registry.py
generative_ai_toolkit/agent/tool.py
generative_ai_toolkit/context/__init__.py
generative_ai_toolkit/conversation_history/__init__.py
generative_ai_toolkit/conversation_history/conversation_history.py
generative_ai_toolkit/evaluate/__init__.py
generative_ai_toolkit/evaluate/evaluate.py
generative_ai_toolkit/evaluate/interactive.py
generative_ai_toolkit/mcp/client.py
generative_ai_toolkit/metrics/__init__.py
generative_ai_toolkit/metrics/base_metric.py
generative_ai_toolkit/metrics/measurement.py
generative_ai_toolkit/metrics/modules/TEMPLATE_metric.py
generative_ai_toolkit/metrics/modules/__init__.py
generative_ai_toolkit/metrics/modules/bleu.py
generative_ai_toolkit/metrics/modules/conciseness.py
generative_ai_toolkit/metrics/modules/conversation.py
generative_ai_toolkit/metrics/modules/cost.py
generative_ai_toolkit/metrics/modules/latency.py
generative_ai_toolkit/metrics/modules/sentiment.py
generative_ai_toolkit/metrics/modules/similarity.py
generative_ai_toolkit/metrics/modules/sql.py
generative_ai_toolkit/metrics/modules/token.py
generative_ai_toolkit/run/__init__.py
generative_ai_toolkit/run/agent.py
generative_ai_toolkit/run/evaluate.py
generative_ai_toolkit/test/__init__.py
generative_ai_toolkit/test/mock.py
generative_ai_toolkit/test/bedrock/__init__.py
generative_ai_toolkit/test/bedrock/bedrock_adapter.py
generative_ai_toolkit/tracer/__init__.py
generative_ai_toolkit/tracer/context.py
generative_ai_toolkit/tracer/dynamodb.py
generative_ai_toolkit/tracer/otlp.py
generative_ai_toolkit/tracer/trace.py
generative_ai_toolkit/tracer/tracer.py
generative_ai_toolkit/ui/__init__.py
generative_ai_toolkit/ui/lib.py
generative_ai_toolkit/ui/ui.py
generative_ai_toolkit-0.23.0.dist-info/licenses/LICENSE
generative_ai_toolkit-0.23.0.dist-info/licenses/NOTICE
generative_ai_toolkit-0.23.0.dist-info/METADATA
generative_ai_toolkit-0.23.0.dist-info/WHEEL
generative_ai_toolkit-0.23.0.dist-info/top_level.txt
generative_ai_toolkit-0.23.0.dist-info/RECORD
