Metadata-Version: 2.4
Name: generative-ai-toolkit
Version: 0.23.0
Summary: Toolkit to support developers in building and operating high quality LLM-based applications
Author-email: Otto Kruse <ottokrus@amazon.nl>, Ryan French <ryanjfre@amazon.co.uk>, Mihai Radulescu Kobler <kobler@amazon.de>, Rui Costa <ruicos@amazon.com>
License: Apache-2.0
Project-URL: Homepage, https://github.com/awslabs/generative-ai-toolkit
Project-URL: Bug Reports, https://github.com/awslabs/generative-ai-toolkit/issues
Project-URL: Source, https://github.com/awslabs/generative-ai-toolkit
Keywords: generative-ai-toolkit,generative-ai,gen-ai,agent,llm,testing
Requires-Python: >=3.13
License-File: LICENSE
License-File: NOTICE
Requires-Dist: boto3<2.0,>=1.37
Provides-Extra: run-agent
Requires-Dist: flask<4.0,>=3.1; extra == "run-agent"
Requires-Dist: gunicorn<24.0,>=23.0; extra == "run-agent"
Requires-Dist: opentelemetry-proto<2.0,>=1.31; extra == "run-agent"
Requires-Dist: pydantic<3.0,>=2.10; extra == "run-agent"
Provides-Extra: evaluate
Requires-Dist: nltk<4.0,>=3.9; extra == "evaluate"
Requires-Dist: scikit-learn<2.0,>=1.5; extra == "evaluate"
Provides-Extra: all
Requires-Dist: generative-ai-toolkit[evaluate,run-agent]; extra == "all"
Requires-Dist: boto3-stubs[bedrock-runtime,dynamodb]<2.0,>=1.37; extra == "all"
Requires-Dist: gradio<6.0,>=5.23; extra == "all"
Requires-Dist: ipython<9.0,>=8.30; extra == "all"
Requires-Dist: mcp<2.0,>=1.8; extra == "all"
Requires-Dist: pandas<3.0,>=2.2; extra == "all"
Requires-Dist: tabulate<1.0,>=0.9; extra == "all"
Provides-Extra: dev
Requires-Dist: generative-ai-toolkit[all]; extra == "dev"
Requires-Dist: playwright<2.0,>=1.52; extra == "dev"
Requires-Dist: pytest<9.0,>=8.4; extra == "dev"
Requires-Dist: pytest-cov<7.0,>=6.2; extra == "dev"
Requires-Dist: pytest-playwright<0.8,>=0.7; extra == "dev"
Requires-Dist: ruff<0.13,>=0.12; extra == "dev"
Dynamic: license-file
